[
 {
  "states_daily":{
   "an":"1",
   "ap":"909",
   "ar":"165",
   "as":"758",
   "br":"14",
   "ch":"2",
   "ct":"68",
   "date":"16-Aug-21",
   "dateymd":"2021-08-16",
   "dd":"0",
   "dl":"27",
   "dn":"2",
   "ga":"62",
   "gj":"14",
   "hp":"276",
   "hr":"22",
   "jh":"35",
   "jk":"77",
   "ka":"1065",
   "kl":"12294",
   "la":"4",
   "ld":"6",
   "mh":"4145",
   "ml":"352",
   "mn":"275",
   "mp":"7",
   "mz":"249",
   "nl":"44",
   "or":"868",
   "pb":"30",
   "py":"49",
   "rj":"11",
   "sk":"20",
   "status":"Confirmed",
   "tg":"405",
   "tn":"1851",
   "tr":"52",
   "tt":"24696",
   "un":"0",
   "up":"17",
   "ut":"18",
   "wb":"502"
  }
 },
 {
  "states_daily":{
   "an":"0",
   "ap":"1543",
   "ar":"249",
   "as":"1014",
   "br":"42",
   "ch":"3",
   "ct":"224",
   "date":"16-Aug-21",
   "dateymd":"2021-08-16",
   "dd":"0",
   "dl":"73",
   "dn":"0",
   "ga":"96",
   "gj":"13",
   "hp":"334",
   "hr":"18",
   "jh":"13",
   "jk":"135",
   "ka":"1486",
   "kl":"18542",
   "la":"9",
   "ld":"6",
   "mh":"5811",
   "ml":"649",
   "mn":"546",
   "mp":"16",
   "mz":"954",
   "nl":"111",
   "or":"1167",
   "pb":"48",
   "py":"86",
   "rj":"44",
   "sk":"147",
   "status":"Recovered",
   "tg":"577",
   "tn":"1911",
   "tr":"223",
   "tt":"36871",
   "un":"0",
   "up":"36",
   "ut":"54",
   "wb":"691"
  }
 },
 {
  "states_daily":{
   "an":"0",
   "ap":"13",
   "ar":"0",
   "as":"10",
   "br":"0",
   "ch":"0",
   "ct":"1",
   "date":"16-Aug-21",
   "dateymd":"2021-08-16",
   "dd":"0",
   "dl":"0",
   "dn":"0",
   "ga":"5",
   "gj":"0",
   "hp":"3",
   "hr":"2",
   "jh":"0",
   "jk":"1",
   "ka":"28",
   "kl":"142",
   "la":"0",
   "ld":"0",
   "mh":"100",
   "ml":"8",
   "mn":"6",
   "mp":"1",
   "mz":"3",
   "nl":"4",
   "or":"66",
   "pb":"2",
   "py":"0",
   "rj":"0",
   "sk":"0",
   "status":"Deceased",
   "tg":"3",
   "tn":"28",
   "tr":"1",
   "tt":"438",
   "un":"0",
   "up":"1",
   "ut":"1",
   "wb":"9"
  }
 }
]